eval_agent/__init__.py
eval_agent/functions.py
tests/__init__.py
tests/test_functions.py
eval_agent-0.1.0.dist-info/METADATA
eval_agent-0.1.0.dist-info/WHEEL
eval_agent-0.1.0.dist-info/top_level.txt
eval_agent-0.1.0.dist-info/RECORD
