Metadata-Version: 2.4
Name: eval_agent
Version: 0.1.0
Author: Naman
Requires-Dist: scikit-learn
Dynamic: author
Dynamic: requires-dist
